ke_ranking_package/__init__.py
ke_ranking_package/config.py
ke_ranking_package/elastic_client.py
ke_ranking_package/helpers.py
ke_ranking_package/paths.py
ke_ranking_package/queries.py
ke_ranking_package/visualize.py
ke_ranking_package-0.0.13.dist-info/LICENSE.md
ke_ranking_package-0.0.13.dist-info/METADATA
ke_ranking_package-0.0.13.dist-info/WHEEL
ke_ranking_package-0.0.13.dist-info/top_level.txt
ke_ranking_package-0.0.13.dist-info/RECORD
